[
  {
    "de": "abbestellen",
    "tr": "ləğv etmək",
    "fav": false
  },
  {
    "de": "Abenteuer",
    "tr": "macəra",
    "fav": false,
    "gender": "das"
  },
  {
    "de": "Abfall",
    "tr": "tullantı, qalıq, qırıntı",
    "fav": false,
    "gender": "der"
  },
  {
    "de": "abgeben",
    "tr": "təslim etmək, vermək",
    "fav": false
  },
  {
    "de": "abgeheftet",
    "tr": "bir yerə qoyulmuş, qaldırmış, sənədə salınmış",
    "fav": false
  },
  {
    "de": "abgelegen",
    "tr": "uzaq",
    "fav": false
  },
  {
    "de": "abgesehen davon, dass",
    "tr": "bu xaric, qaldı ki...",
    "fav": false
  },
  {
    "de": "abhängen von Dat",
    "tr": "asılı olmaq",
    "fav": false
  },
  {
    "de": "abkaufen, jemandem",
    "tr": "kiminsə dediyinə inanmaq",
    "fav": false
  },
  {
    "de": "ablaufen",
    "tr": "olmaq keçmək, günü dolmaq",
    "fav": false
  },
  {
    "de": "ablenken",
    "tr": "diqqətin başqa yönə çevirmək, diqqətin dağıtmaq",
    "fav": false
  },
  {
    "de": "Abnehmen",
    "tr": "kilo atmaq, arıqlamaq",
    "fav": false
  },
  {
    "de": "Abprache",
    "tr": "anlaşma, sözləşmə, razılaşma",
    "fav": false,
    "gender": "die"
  },
  {
    "de": "Absatz",
    "tr": "satış",
    "fav": false,
    "gender": "der"
  },
  {
    "de": "Abschaffung",
    "tr": "ləğv",
    "fav": false,
    "gender": "die"
  },
  {
    "de": "abschicken",
    "tr": "yollamaq, göndərmək",
    "fav": false
  },
  {
    "de": "abschließen",
    "tr": "bitirmək, tamamlamaq, qapatmaq, kilidləmək",
    "fav": false
  },
  {
    "de": "absetzen",
    "tr": "satmaq",
    "fav": false
  },
  {
    "de": "absichern",
    "tr": "qorumaq, sığortalamaq",
    "fav": false
  },
  {
    "de": "abwarten",
    "tr": "sonun gözləmək",
    "fav": false
  },
  {
    "de": "Abwechslung",
    "tr": "dəyişim, dəyişiklik",
    "fav": false,
    "gender": "die"
  },
  {
    "de": "Adäquates, etwas",
    "tr": "uyğun bir şey, eyni, oxşar şey",
    "fav": false
  },
  {
    "de": "Albtraum",
    "tr": "kabus, qorxulu yuxu",
    "fav": false,
    "gender": "der"
  },
  {
    "de": "alleinerziehend",
    "tr": "tənha ana, ya da ata",
    "fav": false
  },
  {
    "de": "alleinstehend",
    "tr": "subay, kimsəsiz",
    "fav": false
  },
  {
    "de": "aller Art",
    "tr": "hər növ",
    "fav": false
  },
  {
    "de": "allerdings",
    "tr": "əslində, bununla bərabər, fəqət",
    "fav": false
  },
  {
    "de": "allerhärtst",
    "tr": "ən çətini, hamısından ağır",
    "fav": false
  },
  {
    "de": "allesamt",
    "tr": "hamısı birdən",
    "fav": false
  },
  {
    "de": "allzu langer Zeit, nicht",
    "tr": "elə də çox zaman, vaxt öncə deyil",
    "fav": false
  },
  {
    "de": "am Himmel",
    "tr": "göy üzündə",
    "fav": false
  },
  {
    "de": "am nächsten stehen",
    "tr": "daha yaxın olmaq",
    "fav": false
  },
  {
    "de": "anbeiden Orten",
    "tr": "hər iki yerdə",
    "fav": false
  },
  {
    "de": "aneignen sich",
    "tr": "əldə etmək, qazanmaq, mənimsəmək",
    "fav": false
  },
  {
    "de": "anfeuern",
    "tr": "ürəkləndirmək",
    "fav": false
  },
  {
    "de": "angeben",
    "tr": "bildirmək",
    "fav": false
  },
  {
    "de": "angegriffen",
    "tr": "yorğun, bitmiş",
    "fav": false
  },
  {
    "de": "angehören + Dat",
    "tr": "aid, mənsub olmaq",
    "fav": false
  },
  {
    "de": "angenehm",
    "tr": "hazır, münasib, xoş, gözəl, razı",
    "fav": false
  },
  {
    "de": "Angst bekommen",
    "tr": "qorxmaq, qorxu yaranmaq",
    "fav": false
  },
  {
    "de": "anhaben",
    "tr": "geyinmiş olmaq, üzərində olmaq",
    "fav": false
  },
  {
    "de": "anhalten zu Dat",
    "tr": "xəbərdarlıq etmək, uyarmaq, tənbeh etmək",
    "fav": false
  },
  {
    "de": "animieren + zu Dat",
    "tr": "həvəsləndirmək, təşviq etmək, istək yaratmaq",
    "fav": false
  },
  {
    "de": "Anleitung",
    "tr": "təlimat",
    "fav": false,
    "gender": "die"
  },
  {
    "de": "annehmen",
    "tr": "qəbul etmək, var saymaq, fərz etmək",
    "fav": false
  },
  {
    "de": "anpacken",
    "tr": "girişmək, başlamaq, tutmaq, yaxalamaq",
    "fav": false
  },
  {
    "de": "anscheinend",
    "tr": "bəlli ki, görünən odur ki",
    "fav": false
  },
  {
    "de": "ansehen",
    "tr": "anlamaq, baxmaq, görmək",
    "fav": false
  },
  {
    "de": "ansehen als Akk",
    "tr": "kimi görmək, kimi baxmaq",
    "fav": false
  },
  {
    "de": "ansetzen",
    "tr": "istifadə etməyə başlamaq, içmək",
    "fav": false
  },
  {
    "de": "Anspruch",
    "tr": "tələb, haqq, iddia, istək",
    "fav": false,
    "gender": "der"
  },
  {
    "de": "anstellen",
    "tr": "açmaq, işlətmək, çalışdırmaq",
    "fav": false
  },
  {
    "de": "anstrengend",
    "tr": "yorucu, əziyyətli",
    "fav": false
  },
  {
    "de": "Anteil haben + an Dat",
    "tr": "payı olmaq",
    "fav": false
  },
  {
    "de": "antreffen",
    "tr": "rastlamaq, qarşılaşmaq",
    "fav": false
  },
  {
    "de": "Anzahl",
    "tr": "say, miqdar",
    "fav": false,
    "gender": "die"
  },
  {
    "de": "Anzug",
    "tr": "köç, daşınma",
    "fav": false,
    "gender": "der"
  },
  {
    "de": "Appell (der) + an Akk",
    "tr": "səsləmə, çağırış, maraq çəkmə, çəkicilik",
    "fav": false
  },
  {
    "de": "Applaus",
    "tr": "alqış",
    "fav": false,
    "gender": "der"
  },
  {
    "de": "Arbeitszeugnis",
    "tr": "iş yerindən arayış",
    "fav": false,
    "gender": "das"
  },
  {
    "de": "Armut",
    "tr": "yoxsulluq",
    "fav": false,
    "gender": "die"
  },
  {
    "de": "atmen",
    "tr": "nəfəs almaq",
    "fav": false
  },
  {
    "de": "aud diese Weise",
    "tr": "bu yolla, bu üsulla, bu tərzdə",
    "fav": false
  },
  {
    "de": "auf einmal",
    "tr": "birdən-birə",
    "fav": false
  },
  {
    "de": "auf Stand-by lassen",
    "tr": "gözləmədə buraxmaq, qoymaq",
    "fav": false
  },
  {
    "de": "aufbrechen",
    "tr": "yola düzəlmək, açılmaq",
    "fav": false
  },
  {
    "de": "aufgeweckt",
    "tr": "oyanır, gözü açıq",
    "fav": false
  },
  {
    "de": "aufgreifen",
    "tr": "mənimsəmək, yaxalamaq, üzərinə almaq",
    "fav": false
  },
  {
    "de": "Aufklärung",
    "tr": "açıqlama",
    "fav": false,
    "gender": "die"
  },
  {
    "de": "Auflistung",
    "tr": "siyahı",
    "fav": false,
    "gender": "die"
  },
  {
    "de": "aufpassen",
    "tr": "diqqət etmək, fikir vermək",
    "fav": false
  },
  {
    "de": "aufpeppen",
    "tr": "yeniləmək, artırmaq, canlandırmaq",
    "fav": false
  },
  {
    "de": "aufreissen",
    "tr": "yaranmaq, söküb almaq, qoparmaq",
    "fav": false
  },
  {
    "de": "aufschreiben",
    "tr": "qeyd etmək, not almaq",
    "fav": false
  },
  {
    "de": "Aufschwung",
    "tr": "yüksəliş, artım",
    "fav": false,
    "gender": "der"
  },
  {
    "de": "aufteilen",
    "tr": "bölüşdürmək, bölmək, parçalamaq",
    "fav": false
  },
  {
    "de": "Auftreten",
    "tr": "çıxış",
    "fav": false,
    "gender": "das"
  },
  {
    "de": "Auftritt",
    "tr": "çıxış",
    "fav": false
  },
  {
    "de": "Auftritt haben",
    "tr": "təqdim etmək",
    "fav": false
  },
  {
    "de": "aufwachsen",
    "tr": "böyümək, yetişmək",
    "fav": false
  },
  {
    "de": "ausbilden sich",
    "tr": "yetişdirmək, böyütmək, əmələ gətirmək",
    "fav": false
  },
  {
    "de": "Ausdauer",
    "tr": "səbr, dayanma gücü",
    "fav": false,
    "gender": "die"
  },
  {
    "de": "ausdrücken",
    "tr": "ifadə etmək",
    "fav": false
  },
  {
    "de": "ausgedehnt",
    "tr": "uzun, geniş, böyük",
    "fav": false
  },
  {
    "de": "ausgehen",
    "tr": "çölə, bayıra çıxmaq, bitmək, qurtarmaq",
    "fav": false
  },
  {
    "de": "ausgehen davon",
    "tr": "fərz etmək, saymaq",
    "fav": false
  },
  {
    "de": "auslösen",
    "tr": "səbəb olmaq, doğurmaq",
    "fav": false
  },
  {
    "de": "ausnutzen",
    "tr": "yararlanmaq, faydalanmaq",
    "fav": false
  },
  {
    "de": "ausscheiden",
    "tr": "çəkilmək, ayrılmaq",
    "fav": false
  },
  {
    "de": "aussehen",
    "tr": "görünmək",
    "fav": false
  },
  {
    "de": "ausstatten",
    "tr": "döşəmək, düzəltmək, düzənləmək",
    "fav": false
  },
  {
    "de": "Ausstellung",
    "tr": "sərgi",
    "fav": false,
    "gender": "die"
  },
  {
    "de": "aussterben",
    "tr": "ortadan qalxmaq, nəsli, soyu tükənmək",
    "fav": false
  },
  {
    "de": "Auswahl an Dat",
    "tr": "çeşid",
    "fav": false,
    "gender": "die"
  },
  {
    "de": "Auswahl treffen (eine)",
    "tr": "seçim etmək",
    "fav": false
  },
  {
    "de": "auswendig lernen",
    "tr": "əzbərləmək, əzbər öyrənmək",
    "fav": false
  },
  {
    "de": "Auszeichnung",
    "tr": "təltif, mükafat",
    "fav": false,
    "gender": "die"
  },
  {
    "de": "Backgammon",
    "tr": "nərd",
    "fav": false
  },
  {
    "de": "Bauer",
    "tr": "kəndli",
    "fav": false,
    "gender": "der"
  },
  {
    "de": "Bauwerk",
    "tr": "bina",
    "fav": false,
    "gender": "das"
  },
  {
    "de": "beachten",
    "tr": "maraqlanmaq, diqqət etmək",
    "fav": false
  },
  {
    "de": "bearbeiten",
    "tr": "işləmək, üzərində çalışmaq",
    "fav": false
  },
  {
    "de": "bebei haben",
    "tr": "yanında olmaq",
    "fav": false
  },
  {
    "de": "befragen",
    "tr": "soruşdurmaq, sorğuya çəkmək",
    "fav": false
  },
  {
    "de": "begabt",
    "tr": "istedadlı",
    "fav": false
  },
  {
    "de": "begeistern + für Akk",
    "tr": "maraqlanmaq, həyəcanlanmaq, coşmaq",
    "fav": false
  },
  {
    "de": "begeistert",
    "tr": "həvəsli, coşqulu, istəkli, coşqun, şövqlə",
    "fav": false
  },
  {
    "de": "begleiten",
    "tr": "müşahidə etmək, yoldaşlıq etmək",
    "fav": false
  },
  {
    "de": "begrenzter Vorrat",
    "tr": "məhdud sayda mal",
    "fav": false
  },
  {
    "de": "behandeln",
    "tr": "müalicə etmək, davranmaq",
    "fav": false
  },
  {
    "de": "beharrlich",
    "tr": "davamlı, israrlı, inadla",
    "fav": false
  },
  {
    "de": "behindert",
    "tr": "şikəst, fiziki qüsurlu",
    "fav": false
  },
  {
    "de": "Beitrag",
    "tr": "ödəniş",
    "fav": false,
    "gender": "der"
  },
  {
    "de": "bekannt sein durch Akk",
    "tr": "nə ilə tanınmaq",
    "fav": false
  },
  {
    "de": "bekannt sein für Akk",
    "tr": "tanınmaq, populyar olmaq",
    "fav": false
  },
  {
    "de": "Bekanntschaft machen",
    "tr": "tanış olmaq",
    "fav": false
  },
  {
    "de": "beklagen + über Akk, sich",
    "tr": "şikayət etmək",
    "fav": false
  },
  {
    "de": "beladen",
    "tr": "yükləmək",
    "fav": false
  },
  {
    "de": "Belange",
    "tr": "maraq, mənfəət, çıxar",
    "fav": false,
    "gender": "die"
  },
  {
    "de": "beliebt",
    "tr": "sevilən, populyar",
    "fav": false
  },
  {
    "de": "beliefern",
    "tr": "göndərmək, təslim etmək",
    "fav": false
  },
  {
    "de": "Belohnung",
    "tr": "ödül, mükafat",
    "fav": false,
    "gender": "die"
  },
  {
    "de": "Beratung",
    "tr": "tövsiyyə",
    "fav": false,
    "gender": "die"
  },
  {
    "de": "Berechnung",
    "tr": "hesab, təxmin, hesablanma",
    "fav": false,
    "gender": "die"
  },
  {
    "de": "berechtigen",
    "tr": "haqlı, ədalətli",
    "fav": false
  },
  {
    "de": "bereits",
    "tr": "artıq",
    "fav": false
  },
  {
    "de": "bereuen",
    "tr": "peşman olmaq",
    "fav": false
  },
  {
    "de": "berichten",
    "tr": "xəbər vermək, anlatmaq",
    "fav": false
  },
  {
    "de": "bescheiden",
    "tr": "qismən",
    "fav": false
  },
  {
    "de": "beschließen",
    "tr": "qərar vermək, son vermək",
    "fav": false
  },
  {
    "de": "beschreiben als",
    "tr": "təsvir etmək",
    "fav": false
  },
  {
    "de": "Besitz",
    "tr": "mülkiyyət, sahiblik",
    "fav": false,
    "gender": "der"
  },
  {
    "de": "besorgen",
    "tr": "təmin etmək, tədarük etmək",
    "fav": false
  },
  {
    "de": "bestehen",
    "tr": "keçmək (imtahandan)",
    "fav": false
  },
  {
    "de": "bestehen in Dat",
    "tr": "bağlı olmaq",
    "fav": false
  },
  {
    "de": "bestimmen",
    "tr": "təyin etmək, təsbit etmək, qərarlaşdırmaq",
    "fav": false
  },
  {
    "de": "bestimmt",
    "tr": "müəyyən, bəlli, mütləq",
    "fav": false
  },
  {
    "de": "beteiligt sein + an Dat",
    "tr": "iştirak etmək, payı olmaq",
    "fav": false
  },
  {
    "de": "betrachten + als",
    "tr": "baxmaq, olaraq görmək",
    "fav": false
  },
  {
    "de": "betragen",
    "tr": "təşkil etmək",
    "fav": false
  },
  {
    "de": "Betreff",
    "tr": "özət, mövzu, problem",
    "fav": false,
    "gender": "der"
  },
  {
    "de": "Betrieb",
    "tr": "firma, müəssisə, idarə",
    "fav": false,
    "gender": "der"
  },
  {
    "de": "betrunken",
    "tr": "sərxoş, içkili",
    "fav": false
  },
  {
    "de": "Bewegung",
    "tr": "hərəkət, idman",
    "fav": false,
    "gender": "die"
  },
  {
    "de": "Beweis",
    "tr": "sübut, dəlil",
    "fav": false,
    "gender": "der"
  },
  {
    "de": "bewerben",
    "tr": "müraciət etmək, baş vurmaq",
    "fav": false
  },
  {
    "de": "Bewerber",
    "tr": "namizəd",
    "fav": false,
    "gender": "der"
  },
  {
    "de": "bewerten",
    "tr": "təxmin etmək, dəyər vermək",
    "fav": false
  },
  {
    "de": "bewundern",
    "tr": "heyran olmaq",
    "fav": false
  },
  {
    "de": "Beziehung (die) + zu Dat",
    "tr": "münasibət",
    "fav": false
  },
  {
    "de": "biegen, sich runter",
    "tr": "aşağı əyilmək",
    "fav": false
  },
  {
    "de": "bilden",
    "tr": "düzəltmək, düzənləmək",
    "fav": false
  },
  {
    "de": "bildlich",
    "tr": "məcazi, simvolik, rəmzi",
    "fav": false
  },
  {
    "de": "bildschön",
    "tr": "mələk kimi, huri kimi",
    "fav": false
  },
  {
    "de": "binden sich",
    "tr": "bağlanmaq, əlaqə yaratmaq",
    "fav": false
  },
  {
    "de": "bis dahin",
    "tr": "daha əvvəl, öncədən, bu zamana qədər",
    "fav": false
  },
  {
    "de": "bitten + um Akk",
    "tr": "xahiş etmək",
    "fav": false
  },
  {
    "de": "Blatt",
    "tr": "vərəq, yarpaq",
    "fav": false,
    "gender": "das"
  },
  {
    "de": "bleiben locker",
    "tr": "sakit, soyuqqanlı qalmaq",
    "fav": false
  },
  {
    "de": "bleich",
    "tr": "solğun",
    "fav": false
  },
  {
    "de": "bloß",
    "tr": "ancaq, yalnız",
    "fav": false
  },
  {
    "de": "Blut machen (gutes)",
    "tr": "kefin açmaq",
    "fav": false
  },
  {
    "de": "blöd",
    "tr": "axmaq, can sıxıcı",
    "fav": false
  },
  {
    "de": "blühen",
    "tr": "açmaq, çiçək açmaq",
    "fav": false
  },
  {
    "de": "boomen",
    "tr": "yüksəlmək, partlatmaq",
    "fav": false
  },
  {
    "de": "Boot",
    "tr": "qayıq",
    "fav": false,
    "gender": "das"
  },
  {
    "de": "Botschaft",
    "tr": "mesaj, səfirlik",
    "fav": false,
    "gender": "die"
  },
  {
    "de": "Branche",
    "tr": "sektor, sahə",
    "fav": false,
    "gender": "die"
  },
  {
    "de": "Bruchteil",
    "tr": "bölüm, qism",
    "fav": false,
    "gender": "der"
  },
  {
    "de": "Brücke",
    "tr": "körpü",
    "fav": false,
    "gender": "die"
  },
  {
    "de": "Buchführung",
    "tr": "mühasibat",
    "fav": false,
    "gender": "die"
  },
  {
    "de": "bunt",
    "tr": "əlvan, rəngli",
    "fav": false
  },
  {
    "de": "Burg",
    "tr": "qəsəbə, şəhər",
    "fav": false,
    "gender": "die"
  },
  {
    "de": "Bühne",
    "tr": "səhnə",
    "fav": false,
    "gender": "die"
  },
  {
    "de": "Bühnenbild",
    "tr": "dekor",
    "fav": false,
    "gender": "das"
  },
  {
    "de": "dabeihaben",
    "tr": "yanında olmaq",
    "fav": false
  },
  {
    "de": "Dach",
    "tr": "dam, çatı",
    "fav": false,
    "gender": "das"
  },
  {
    "de": "dafür sein",
    "tr": "lehinə olmaq",
    "fav": false
  },
  {
    "de": "dank + Gen",
    "tr": "sayəsində",
    "fav": false
  },
  {
    "de": "dankbar sein",
    "tr": "minnatdar olmaq",
    "fav": false
  },
  {
    "de": "Darauf kommt’s an",
    "tr": "bundan asılıdır",
    "fav": false
  },
  {
    "de": "darstellen",
    "tr": "canlandırmaq, göstərmək",
    "fav": false
  },
  {
    "de": "darüber hinaus",
    "tr": "ayrıca, bundan başqa",
    "fav": false
  },
  {
    "de": "Datei",
    "tr": "sənəd",
    "fav": false,
    "gender": "die"
  },
  {
    "de": "Dauerlob",
    "tr": "daimi tərif",
    "fav": false,
    "gender": "das"
  },
  {
    "de": "Decke",
    "tr": "örtük, yorğan",
    "fav": false,
    "gender": "die"
  },
  {
    "de": "dem Zufall überlassen",
    "tr": "təsadüfə buraxmaq",
    "fav": false
  },
  {
    "de": "dennoch",
    "tr": "yenə də, buna rəğmən, buna qarşı",
    "fav": false
  },
  {
    "de": "derzeitig",
    "tr": "indiki, hal-hazırki, gerçək, o zamankı",
    "fav": false
  },
  {
    "de": "deswegen",
    "tr": "buna görə",
    "fav": false
  },
  {
    "de": "Dicke Freunde",
    "tr": "canciyər dostlar",
    "fav": false
  },
  {
    "de": "dienen als",
    "tr": "xidmət etmək",
    "fav": false
  },
  {
    "de": "Dienste",
    "tr": "xidmət, servis",
    "fav": false,
    "gender": "die"
  },
  {
    "de": "Direktflug",
    "tr": "birbaşa uçuş",
    "fav": false,
    "gender": "der"
  },
  {
    "de": "doppelt",
    "tr": "ikiqat",
    "fav": false
  },
  {
    "de": "Dorf",
    "tr": "kənd",
    "fav": false,
    "gender": "das"
  },
  {
    "de": "Drachen",
    "tr": "çərpələng",
    "fav": false,
    "gender": "der"
  },
  {
    "de": "dran sein",
    "tr": "sırada olmaq, növbəsi olmaq",
    "fav": false
  },
  {
    "de": "Dreck",
    "tr": "kir, çirk",
    "fav": false,
    "gender": "der"
  },
  {
    "de": "dringen durch Akk",
    "tr": "nüfuz etmək",
    "fav": false
  },
  {
    "de": "dringend",
    "tr": "təcili, məcburi",
    "fav": false
  },
  {
    "de": "Druck",
    "tr": "təzyiq, basğı",
    "fav": false,
    "gender": "der"
  },
  {
    "de": "drängen",
    "tr": "basqı etmək, sıxışdırmaq",
    "fav": false
  },
  {
    "de": "drücken auf Akk",
    "tr": "basmaq",
    "fav": false
  },
  {
    "de": "Duchschnitt (im)",
    "tr": "ortalama olaraq",
    "fav": false
  },
  {
    "de": "dumm",
    "tr": "axmaq",
    "fav": false
  },
  {
    "de": "durch den Wind sein",
    "tr": "sinirli, özündə olmamaq",
    "fav": false
  },
  {
    "de": "durch die Reihen",
    "tr": "sıralarla cərgələrlə",
    "fav": false
  },
  {
    "de": "durch etwas müssen",
    "tr": "bacarmaq, bitirmək",
    "fav": false
  },
  {
    "de": "Durchblick",
    "tr": "mənzərə, görünüş",
    "fav": false,
    "gender": "der"
  },
  {
    "de": "Durchblutung",
    "tr": "qandövranı",
    "fav": false,
    "gender": "die"
  },
  {
    "de": "durcheinander",
    "tr": "dağınıq, qarmaqarışıq, çaşmış",
    "fav": false
  },
  {
    "de": "durchführen",
    "tr": "tətbiq etmək, keçirmək, icra etmək",
    "fav": false
  },
  {
    "de": "durchsehen (trennbar)",
    "tr": "gözdən keçirtmək",
    "fav": false
  },
  {
    "de": "durstig sein",
    "tr": "susamış",
    "fav": false
  },
  {
    "de": "dämlich",
    "tr": "axmaq, inadçı",
    "fav": false
  },
  {
    "de": "Dürre",
    "tr": "quraqlıq",
    "fav": false,
    "gender": "die"
  },
  {
    "de": "Ebene",
    "tr": "səviyyə, sahə",
    "fav": false,
    "gender": "die"
  },
  {
    "de": "ebenfalls",
    "tr": "eyni zamanda, həm də",
    "fav": false
  },
  {
    "de": "echt",
    "tr": "xalis, əsl",
    "fav": false
  },
  {
    "de": "Echtheit",
    "tr": "gerçəklik, həqiqət, orijinallıq",
    "fav": false,
    "gender": "die"
  },
  {
    "de": "Ecke",
    "tr": "küncdə, kənarda (um die Ecke)",
    "fav": false,
    "gender": "die"
  },
  {
    "de": "edel",
    "tr": "mükəmməl, qiymətli, super, bol, zəngin",
    "fav": false
  },
  {
    "de": "ehrgeizig",
    "tr": "əzmli, həvəsli, coşqun",
    "fav": false
  },
  {
    "de": "ehrlich",
    "tr": "namuslu, dürüst, səmimi",
    "fav": false
  },
  {
    "de": "eigentlich",
    "tr": "əsas, əslində",
    "fav": false
  },
  {
    "de": "ein Drittel",
    "tr": "üçdə bir",
    "fav": false
  },
  {
    "de": "Eindruck",
    "tr": "təəssürat",
    "fav": false,
    "gender": "der"
  },
  {
    "de": "einfatlen + Dat",
    "tr": "yada düşmək",
    "fav": false
  },
  {
    "de": "eingehen",
    "tr": "gəlmək, daxil olmaq, əlavə etmək",
    "fav": false
  },
  {
    "de": "einladen + zu Dat",
    "tr": "çağırmaq, dəvət etmək",
    "fav": false
  },
  {
    "de": "einprägen, sich",
    "tr": "əzbərləmək",
    "fav": false
  },
  {
    "de": "einrichten",
    "tr": "döşəmək, düzəltmək, düzənləmək",
    "fav": false
  },
  {
    "de": "einsam",
    "tr": "tənha",
    "fav": false
  },
  {
    "de": "Einsamkeit",
    "tr": "tənhalıq",
    "fav": false,
    "gender": "die"
  },
  {
    "de": "Einsatz",
    "tr": "əməliyyat, iş",
    "fav": false,
    "gender": "der"
  },
  {
    "de": "einschenken",
    "tr": "boşaltmaq, tökmək, doldurmaq",
    "fav": false
  },
  {
    "de": "einstellen auf Akk sich",
    "tr": "hazırlanmaq, uyğunlaşmaq",
    "fav": false
  },
  {
    "de": "Einstieg schaffen + in Akk (den)",
    "tr": "atılmaq, girişmək",
    "fav": false
  },
  {
    "de": "einstimmen auf Akk, sich",
    "tr": "ayaqlaşmaq, uyğunlaşmaq",
    "fav": false
  },
  {
    "de": "eintreten in Akk",
    "tr": "daxil olmaq, girmək",
    "fav": false
  },
  {
    "de": "einwickeln",
    "tr": "aldatmaq",
    "fav": false
  },
  {
    "de": "Einzelstück",
    "tr": "nadir parça",
    "fav": false,
    "gender": "das"
  },
  {
    "de": "ekelig",
    "tr": "iyrənc",
    "fav": false
  },
  {
    "de": "Empfehlung",
    "tr": "tövsiyyə",
    "fav": false,
    "gender": "die"
  },
  {
    "de": "empfinden",
    "tr": "anlamaq, hiss etmək",
    "fav": false
  },
  {
    "de": "endlos",
    "tr": "sonsuz, bitməz",
    "fav": false
  },
  {
    "de": "Engagement",
    "tr": "məsuliyyət, iş",
    "fav": false,
    "gender": "das"
  },
  {
    "de": "Enkel",
    "tr": "nəvə",
    "fav": false,
    "gender": "der"
  },
  {
    "de": "enorm",
    "tr": "çox böyük",
    "fav": false
  },
  {
    "de": "entdecken",
    "tr": "kəşf etmək, tapmaq",
    "fav": false
  },
  {
    "de": "entfalten",
    "tr": "açmaq, yaymaq, ortaya çıxartmaq",
    "fav": false
  },
  {
    "de": "entfernen",
    "tr": "çıxartmaq, uzaqlaşdırmaq",
    "fav": false
  },
  {
    "de": "enthalten",
    "tr": "tərkibində olmaq, içində olmaq",
    "fav": false
  },
  {
    "de": "entladen",
    "tr": "boşaltmaq",
    "fav": false
  },
  {
    "de": "entlasten",
    "tr": "rahatlatmaq, yardım etmək",
    "fav": false
  },
  {
    "de": "entscheiden",
    "tr": "qərar vermək",
    "fav": false
  },
  {
    "de": "Entscheidung fällen",
    "tr": "qərar vermək, qərar almaq",
    "fav": false
  },
  {
    "de": "entsorgen",
    "tr": "yox etmək, ortadan qaldırmaq",
    "fav": false
  },
  {
    "de": "entspannen, sich",
    "tr": "rahatlamaq",
    "fav": false
  },
  {
    "de": "entsprechen + Dat",
    "tr": "uyğun olmaq, bənzəmək",
    "fav": false
  },
  {
    "de": "entstehen",
    "tr": "meydana gəlmək, qaynaqlanmaq",
    "fav": false
  },
  {
    "de": "enttäuscht",
    "tr": "xəyal qırıqlığına uğramış",
    "fav": false
  },
  {
    "de": "erbauen",
    "tr": "qurma, inşa etmək",
    "fav": false
  },
  {
    "de": "Erbe",
    "tr": "miras",
    "fav": false,
    "gender": "das"
  },
  {
    "de": "erben",
    "tr": "miras olaraq almaq",
    "fav": false
  },
  {
    "de": "Erde",
    "tr": "yer üzü, torpaq, yer",
    "fav": false,
    "gender": "die"
  },
  {
    "de": "Ereignis",
    "tr": "hadisə, olay",
    "fav": false,
    "gender": "das"
  },
  {
    "de": "erfahren",
    "tr": "öyrənmək, təcrübə etmək",
    "fav": false
  },
  {
    "de": "erfolgen",
    "tr": "olmaq, çıxmaq, ardından gəlmək",
    "fav": false
  },
  {
    "de": "Erfolglosigkeit",
    "tr": "uğursuzluq",
    "fav": false,
    "gender": "die"
  },
  {
    "de": "erfolgreich",
    "tr": "müvəffəqiyyətlə, uğurlu",
    "fav": false
  },
  {
    "de": "erfrischen",
    "tr": "sərinlətmək, canlandırmaq",
    "fav": false
  },
  {
    "de": "erfüllen",
    "tr": "gerçəkləşmək, yerinə gəlmək",
    "fav": false
  },
  {
    "de": "erhärten",
    "tr": "bütünləşdirmək, qətiləşdirmək, sərtləşdirmək",
    "fav": false
  },
  {
    "de": "erhöhen",
    "tr": "qalxmaq, artmaq, çoxalmaq",
    "fav": false
  },
  {
    "de": "erkennen an Dat",
    "tr": "bir şeydən tanımaq",
    "fav": false
  },
  {
    "de": "Erkenntnis",
    "tr": "məlumat, bilgi",
    "fav": false,
    "gender": "die"
  },
  {
    "de": "erkunden",
    "tr": "soruşub öyrənmək, ortaya çıxartmaq",
    "fav": false
  },
  {
    "de": "erlauben",
    "tr": "icazə vermək, içəri buraxmaq, izn vermək (zulassen)",
    "fav": false
  },
  {
    "de": "erleben",
    "tr": "yaşamaq, görmək, keçirmək",
    "fav": false
  },
  {
    "de": "Erlebnis",
    "tr": "macəra",
    "fav": false,
    "gender": "das"
  },
  {
    "de": "erledigen",
    "tr": "tamamlamaq, yerinə yetirmək",
    "fav": false
  },
  {
    "de": "erleichtern",
    "tr": "asanlaşdırmaq, sadələşdirmək",
    "fav": false
  },
  {
    "de": "ermordern",
    "tr": "öldürmək, qətletmək",
    "fav": false
  },
  {
    "de": "erneuerbar",
    "tr": "yenilənən, tükənməyən",
    "fav": false
  },
  {
    "de": "ernst nehmen",
    "tr": "ciddiyə almaq",
    "fav": false
  },
  {
    "de": "Ernährung",
    "tr": "qidalanma",
    "fav": false,
    "gender": "die"
  },
  {
    "de": "Ernüchterung",
    "tr": "məyusluq",
    "fav": false,
    "gender": "die"
  },
  {
    "de": "erschrecken",
    "tr": "ürkmək, qorxmaq",
    "fav": false
  },
  {
    "de": "erschöpft",
    "tr": "yorğun, bitkin",
    "fav": false
  },
  {
    "de": "ersetzen + durch Akk",
    "tr": "yerinə keçmək, dəyişmək, əvəz etmək",
    "fav": false
  },
  {
    "de": "ersparen sich",
    "tr": "özünə saxlamaq",
    "fav": false
  },
  {
    "de": "erst",
    "tr": "hər şeydən öncə, ilk olaraq",
    "fav": false
  },
  {
    "de": "erstaunlich",
    "tr": "inanılmaz, heyrətamiz, maraqlı",
    "fav": false
  },
  {
    "de": "erstellen",
    "tr": "hazırlamaq",
    "fav": false
  },
  {
    "de": "Ertrinken",
    "tr": "boğulma",
    "fav": false,
    "gender": "das"
  },
  {
    "de": "erwachen",
    "tr": "oyanmaq",
    "fav": false
  },
  {
    "de": "erwischen",
    "tr": "yaxalamaq, tutmaq",
    "fav": false
  },
  {
    "de": "erwähnen",
    "tr": "söz etmək, anmaq",
    "fav": false
  },
  {
    "de": "erwünscht sein",
    "tr": "xoş, arzu edilən, məqbul",
    "fav": false
  },
  {
    "de": "erziehen",
    "tr": "tərbiyə etmək, böyütmək",
    "fav": false
  },
  {
    "de": "Es stimmt",
    "tr": "eynən, düzdür, elədir",
    "fav": false
  },
  {
    "de": "ewig",
    "tr": "əbədi",
    "fav": false
  },
  {
    "de": "Existenz",
    "tr": "dolanışıq, keçim",
    "fav": false,
    "gender": "die"
  },
  {
    "de": "Fachmann",
    "tr": "mütəxəssis, peşəkar",
    "fav": false,
    "gender": "der"
  },
  {
    "de": "fassen",
    "tr": "tutmaq, yaxalamaq",
    "fav": false
  },
  {
    "de": "faszinieren",
    "tr": "cəzb etmək, heyran etmək",
    "fav": false
  },
  {
    "de": "Fazit",
    "tr": "nəticə",
    "fav": false,
    "gender": "das"
  },
  {
    "de": "fehlen + Dat",
    "tr": "olmamaq, əksik olmaq",
    "fav": false
  },
  {
    "de": "Fehler",
    "tr": "səhv, yalnış, xəta",
    "fav": false,
    "gender": "der"
  },
  {
    "de": "fein",
    "tr": "kübar, həssas, zövqlü və s",
    "fav": false
  },
  {
    "de": "fertig werden + mit Dat",
    "tr": "bitirmək, öhdəsindən gəlmək",
    "fav": false
  },
  {
    "de": "fest etablieren",
    "tr": "sıx yerləşmək",
    "fav": false
  },
  {
    "de": "festhalten",
    "tr": "sözə tutmaq, bərk tutmaq, yaxalamaq",
    "fav": false
  },
  {
    "de": "feststellen",
    "tr": "təsbit etmək, bəyan etmək, ortaya çıxartmaq",
    "fav": false
  },
  {
    "de": "Flatrate",
    "tr": "sabit qiymət",
    "fav": false,
    "gender": "die"
  },
  {
    "de": "Fleck",
    "tr": "ləkə",
    "fav": false,
    "gender": "der"
  },
  {
    "de": "Flieger",
    "tr": "sürət qatarı, pilot",
    "fav": false,
    "gender": "der"
  },
  {
    "de": "Fluggesellschaft",
    "tr": "hava yolu şirkəti, avia şirkət",
    "fav": false,
    "gender": "die"
  },
  {
    "de": "Fluss",
    "tr": "çay",
    "fav": false,
    "gender": "der"
  },
  {
    "de": "Folge",
    "tr": "nəticə, sonuc, sıra",
    "fav": false,
    "gender": "die"
  },
  {
    "de": "Folgejahr",
    "tr": "sonrakı il",
    "fav": false,
    "gender": "das"
  },
  {
    "de": "folglich",
    "tr": "buna görə, bundan dolayı, bu üzdən",
    "fav": false
  },
  {
    "de": "fordern",
    "tr": "istəmək, tələb etmək",
    "fav": false
  },
  {
    "de": "fortsetzen",
    "tr": "davam etmək",
    "fav": false
  },
  {
    "de": "fressen",
    "tr": "yemək, tıxmaq",
    "fav": false
  },
  {
    "de": "Frieden",
    "tr": "sülh",
    "fav": false,
    "gender": "der"
  },
  {
    "de": "frisieren",
    "tr": "saçın düzəltmək",
    "fav": false
  },
  {
    "de": "froh sein + über Akk",
    "tr": "məmnun olmaq",
    "fav": false
  },
  {
    "de": "Frustration",
    "tr": "xəyal qırıqlığı, məyusluq",
    "fav": false,
    "gender": "die"
  },
  {
    "de": "Futter",
    "tr": "yem",
    "fav": false,
    "gender": "das"
  },
  {
    "de": "Fußboden",
    "tr": "döşəmə, yer",
    "fav": false,
    "gender": "der"
  },
  {
    "de": "fördern",
    "tr": "faydalı olmaq, dəstəkləmək",
    "fav": false
  },
  {
    "de": "Förderung",
    "tr": "dəstək, yardım",
    "fav": false,
    "gender": "die"
  },
  {
    "de": "führen zu Dat",
    "tr": "səbəb olmaq, gətirib çıxarmaq",
    "fav": false
  },
  {
    "de": "Gastgeber",
    "tr": "ev sahibi",
    "fav": false,
    "gender": "der"
  },
  {
    "de": "gebildet",
    "tr": "təhsilli, oxumuş",
    "fav": false
  },
  {
    "de": "Geburt",
    "tr": "doğum, doğuş",
    "fav": false,
    "gender": "die"
  },
  {
    "de": "Gedanke",
    "tr": "fikir, düşüncə",
    "fav": false,
    "gender": "der"
  },
  {
    "de": "Gedächtnis",
    "tr": "yaddaş",
    "fav": false,
    "gender": "das"
  },
  {
    "de": "Gefahr",
    "tr": "təhlükə",
    "fav": false,
    "gender": "die"
  },
  {
    "de": "gefallen + Dat",
    "tr": "xoşuna gəlmək",
    "fav": false
  },
  {
    "de": "gefordert",
    "tr": "gərəkli, lazımlı, istənən",
    "fav": false
  },
  {
    "de": "Geheimnis",
    "tr": "sirr",
    "fav": false,
    "gender": "das"
  },
  {
    "de": "geheimnisvoll",
    "tr": "gizli, əsrarəngiz, mistik",
    "fav": false
  },
  {
    "de": "gehen nahe",
    "tr": "təsir etmək",
    "fav": false
  },
  {
    "de": "geil",
    "tr": "əla",
    "fav": false
  },
  {
    "de": "Geisteshaltung",
    "tr": "anlayış, düşüncə, zehniyyət",
    "fav": false,
    "gender": "die"
  },
  {
    "de": "geistigen Fähigkeiten",
    "tr": "zehni, əqli bacarıqlar",
    "fav": false,
    "gender": "die"
  },
  {
    "de": "geistreich",
    "tr": "ağıllı, zəki",
    "fav": false
  },
  {
    "de": "gelassen nehmen",
    "tr": "soyuqqanlı qəbul etmək",
    "fav": false
  },
  {
    "de": "Gelassenheit",
    "tr": "sakitlik, soyuqqanlılıq",
    "fav": false,
    "gender": "die"
  },
  {
    "de": "gelten als",
    "tr": "sayılmaq",
    "fav": false
  },
  {
    "de": "gemeinsam",
    "tr": "ortaq, birlikdə",
    "fav": false
  },
  {
    "de": "Gemeinschaft",
    "tr": "toplum, cəmiyyət",
    "fav": false,
    "gender": "die"
  },
  {
    "de": "generell",
    "tr": "təqribi, ümumiyyətlə",
    "fav": false
  },
  {
    "de": "genervt",
    "tr": "sıxıntılı, qızğın, sinirli",
    "fav": false
  },
  {
    "de": "genießen",
    "tr": "həzz, ləzzət almaq, dadın çıxartmaq",
    "fav": false
  },
  {
    "de": "geordnet",
    "tr": "düzənli",
    "fav": false
  },
  {
    "de": "gepaart mit",
    "tr": "bağlı, birləşmiş",
    "fav": false
  },
  {
    "de": "gepflegt",
    "tr": "yaxşı geyimli, baxımlı, mədəni",
    "fav": false
  },
  {
    "de": "gerade",
    "tr": "hələ, tam",
    "fav": false
  },
  {
    "de": "geraten",
    "tr": "düşmək, qapılmaq (in Akk)",
    "fav": false
  },
  {
    "de": "gereizt",
    "tr": "sinirli, dırdır edən, sözə baxmaz",
    "fav": false
  },
  {
    "de": "gering",
    "tr": "az, cüzi, adi",
    "fav": false
  },
  {
    "de": "geringfügig",
    "tr": "önəmsiz, kiçik, az",
    "fav": false
  },
  {
    "de": "Geräusch",
    "tr": "səs, gurultu",
    "fav": false,
    "gender": "das"
  },
  {
    "de": "Gerücht",
    "tr": "dedi-qodu",
    "fav": false,
    "gender": "das"
  },
  {
    "de": "geschehen",
    "tr": "baş vermək",
    "fav": false
  },
  {
    "de": "gescheit",
    "tr": "ağıllı, zəki, nəşəli",
    "fav": false
  },
  {
    "de": "Geschirr",
    "tr": "qab-qacaq",
    "fav": false,
    "gender": "das"
  },
  {
    "de": "Gesicht",
    "tr": "üz, sifət, surət, çöhrə",
    "fav": false,
    "gender": "das"
  },
  {
    "de": "Gespräche führen",
    "tr": "danışıqlar aparmaq",
    "fav": false
  },
  {
    "de": "Gestalten",
    "tr": "düzətmə, təşkil etmə",
    "fav": false,
    "gender": "das"
  },
  {
    "de": "gestapelt",
    "tr": "yığılmış",
    "fav": false
  },
  {
    "de": "gestehen",
    "tr": "etiraf etmək",
    "fav": false
  },
  {
    "de": "gestrickt",
    "tr": "toxunma, toxunmuş",
    "fav": false
  },
  {
    "de": "gestrig",
    "tr": "dünənki",
    "fav": false
  },
  {
    "de": "gewinnen",
    "tr": "qazanmaq, udmaq",
    "fav": false
  },
  {
    "de": "gewiss",
    "tr": "əmin, məlum, bəlli",
    "fav": false
  },
  {
    "de": "Gewissen",
    "tr": "vicdan",
    "fav": false,
    "gender": "das"
  },
  {
    "de": "gewöhnen an Akk, sich",
    "tr": "alışmaq, vərdiş etmək",
    "fav": false
  },
  {
    "de": "Gipfel",
    "tr": "zirvə",
    "fav": false,
    "gender": "der"
  },
  {
    "de": "glanzvoll",
    "tr": "parlaq, çəkici",
    "fav": false
  },
  {
    "de": "glatt",
    "tr": "düz",
    "fav": false
  },
  {
    "de": "gleich bleiben",
    "tr": "dəyişməmək, sabit qalmaq",
    "fav": false
  },
  {
    "de": "Gleichstellung",
    "tr": "bərabərlik",
    "fav": false,
    "gender": "die"
  },
  {
    "de": "gleichzeitig",
    "tr": "eyni zamanda",
    "fav": false
  },
  {
    "de": "Glühbirne",
    "tr": "lampa",
    "fav": false,
    "gender": "die"
  },
  {
    "de": "Greifen nach Dat",
    "tr": "əl uzatmaq",
    "fav": false
  },
  {
    "de": "grenzenlos",
    "tr": "sonsuz, sərhədsiz",
    "fav": false
  },
  {
    "de": "griffbereit",
    "tr": "hazır, əlaltda",
    "fav": false
  },
  {
    "de": "großartig",
    "tr": "mükəmməl",
    "fav": false
  },
  {
    "de": "großzügig",
    "tr": "comərd",
    "fav": false
  },
  {
    "de": "Gründer",
    "tr": "qurucu",
    "fav": false,
    "gender": "der"
  },
  {
    "de": "gucken",
    "tr": "baxmaq",
    "fav": false
  },
  {
    "de": "gut aussehend",
    "tr": "yaraşıqlı",
    "fav": false
  },
  {
    "de": "gut drauf sein",
    "tr": "kefi yaxşı olmaq",
    "fav": false
  },
  {
    "de": "gut gelaunt sein",
    "tr": "əhvalı yaxşı olmaq",
    "fav": false
  },
  {
    "de": "guttun + Dat",
    "tr": "yaratmaq",
    "fav": false
  },
  {
    "de": "Güter",
    "tr": "mallar",
    "fav": false
  },
  {
    "de": "Hafen",
    "tr": "liman",
    "fav": false,
    "gender": "der"
  },
  {
    "de": "halten",
    "tr": "düşünmək, zənn etmək",
    "fav": false
  },
  {
    "de": "handeln",
    "tr": "hərəkətə keçmək, davranmaq",
    "fav": false
  },
  {
    "de": "handwerklich",
    "tr": "əl sənəti, əlişi",
    "fav": false
  },
  {
    "de": "Haufen",
    "tr": "yığın, basabas",
    "fav": false,
    "gender": "der"
  },
  {
    "de": "Heft",
    "tr": "broşür, kitabça, dəftər, buklet",
    "fav": false,
    "gender": "das"
  },
  {
    "de": "heftig",
    "tr": "şiddətli, sərt",
    "fav": false
  },
  {
    "de": "heikel",
    "tr": "çətin, müşkül",
    "fav": false
  },
  {
    "de": "heilen",
    "tr": "sağaltmaq",
    "fav": false
  },
  {
    "de": "Heimweh",
    "tr": "vətən həsrəti",
    "fav": false,
    "gender": "das"
  },
  {
    "de": "Heirat",
    "tr": "evlilik",
    "fav": false,
    "gender": "die"
  },
  {
    "de": "Heizung",
    "tr": "isitmə",
    "fav": false,
    "gender": "die"
  },
  {
    "de": "Held",
    "tr": "qəhrəman",
    "fav": false,
    "gender": "der"
  },
  {
    "de": "heldenhaft",
    "tr": "cəsurca, qəhrəmanca",
    "fav": false
  },
  {
    "de": "herausziehen",
    "tr": "çıxarmaq",
    "fav": false
  },
  {
    "de": "Herde",
    "tr": "sürü",
    "fav": false,
    "gender": "die"
  },
  {
    "de": "Herkunft",
    "tr": "soy, əsil, qaynaq",
    "fav": false,
    "gender": "die"
  },
  {
    "de": "herlaufen",
    "tr": "arxasınca düşmək",
    "fav": false
  },
  {
    "de": "herrenlos",
    "tr": "sahibsiz",
    "fav": false
  },
  {
    "de": "herumstehen",
    "tr": "ayaq altında dolanmaq",
    "fav": false
  },
  {
    "de": "herzlich",
    "tr": "səmimi, içdən, candan",
    "fav": false
  },
  {
    "de": "Heulen",
    "tr": "ulama, ağlama",
    "fav": false,
    "gender": "das"
  },
  {
    "de": "heutig",
    "tr": "bugünkü",
    "fav": false
  },
  {
    "de": "hinaus",
    "tr": "bayıra, çölə, xaricə",
    "fav": false
  },
  {
    "de": "hingehen",
    "tr": "getmək",
    "fav": false
  },
  {
    "de": "hintereinander",
    "tr": "arxa-arxaya, ard-arda",
    "fav": false
  },
  {
    "de": "hinterherlaufen + Dat",
    "tr": "arxasından qaçmaq",
    "fav": false
  },
  {
    "de": "hochwertig",
    "tr": "yüksək keyfiyyətli",
    "fav": false
  },
  {
    "de": "Hof",
    "tr": "saray, həyət",
    "fav": false,
    "gender": "der"
  },
  {
    "de": "Hoffnung",
    "tr": "ümid",
    "fav": false,
    "gender": "die"
  },
  {
    "de": "holen",
    "tr": "alıb gətirmək, gedib gətirmək",
    "fav": false
  },
  {
    "de": "Huhn",
    "tr": "toyuq",
    "fav": false,
    "gender": "das"
  },
  {
    "de": "höflich",
    "tr": "kübar, sayğılı",
    "fav": false
  },
  {
    "de": "hüten",
    "tr": "saxlamaq, nəzarət etmək, qorumaq",
    "fav": false
  },
  {
    "de": "Hütte",
    "tr": "viranə, daxma",
    "fav": false,
    "gender": "die"
  },
  {
    "de": "immerhin",
    "tr": "buna rəğmən, nə də olsa, heç olmazsa",
    "fav": false
  },
  {
    "de": "Interesse wecken",
    "tr": "maraq oyatmaq",
    "fav": false,
    "gender": "das"
  },
  {
    "de": "Intoleranz",
    "tr": "dayanmama, dözməmə, təhəmmül etməmə",
    "fav": false,
    "gender": "die"
  },
  {
    "de": "irgendetwas",
    "tr": "nəsə",
    "fav": false
  },
  {
    "de": "irgendwelche",
    "tr": "hər hansı",
    "fav": false
  },
  {
    "de": "irrtumlich",
    "tr": "yanlışlıqla",
    "fav": false
  },
  {
    "de": "jedoch",
    "tr": "fəqət, bununla birlikdə, halbuki",
    "fav": false
  },
  {
    "de": "kaum",
    "tr": "gücbəla ilə, çətin",
    "fav": false
  },
  {
    "de": "kein Ende nehmen",
    "tr": "bitməmək, sonlanmamaq",
    "fav": false
  },
  {
    "de": "Kette",
    "tr": "zəncir, şəbəkə",
    "fav": false,
    "gender": "die"
  },
  {
    "de": "Klatsch",
    "tr": "söhbət, dedi qodu, qeybət",
    "fav": false,
    "gender": "der"
  },
  {
    "de": "klicken",
    "tr": "basmaq, tıqqıldatmaq",
    "fav": false
  },
  {
    "de": "Klingel",
    "tr": "zınqırov, zil",
    "fav": false,
    "gender": "die"
  },
  {
    "de": "knapp",
    "tr": "az, qısa, güclə",
    "fav": false
  },
  {
    "de": "Kneipe",
    "tr": "meyxana",
    "fav": false,
    "gender": "die"
  },
  {
    "de": "Knick",
    "tr": "maraq, boşluq, çatlaq, bükülmə",
    "fav": false,
    "gender": "der"
  },
  {
    "de": "komischerweise",
    "tr": "nə qəribədir ki",
    "fav": false
  },
  {
    "de": "Kopf frei kriegen (den)",
    "tr": "başın rahatlığın istəmək",
    "fav": false
  },
  {
    "de": "kostenpflichtig",
    "tr": "ödənişli, hücrətli",
    "fav": false
  },
  {
    "de": "Kraft",
    "tr": "qüvvə, güc",
    "fav": false,
    "gender": "die"
  },
  {
    "de": "Kraft tanken",
    "tr": "güc almaq, güc yığmaq",
    "fav": false
  },
  {
    "de": "kratzig",
    "tr": "tikanlı, iynə kimi",
    "fav": false
  },
  {
    "de": "Kreißsaal",
    "tr": "doğum otağı",
    "fav": false,
    "gender": "der"
  },
  {
    "de": "kurz darauf",
    "tr": "bundan az sonra",
    "fav": false
  },
  {
    "de": "kämpfen mit + Dativ",
    "tr": "mübarizə aparmaq",
    "fav": false
  },
  {
    "de": "Köstlichkeit",
    "tr": "ləzzət",
    "fav": false,
    "gender": "die"
  },
  {
    "de": "kündigen",
    "tr": "işdən çıxdığın bildirmək",
    "fav": false
  },
  {
    "de": "künstlich",
    "tr": "süni, saxta, yalançı",
    "fav": false
  },
  {
    "de": "Laden",
    "tr": "mağaza",
    "fav": false,
    "gender": "der"
  },
  {
    "de": "lagern",
    "tr": "depo etmək, anbara qoymaq",
    "fav": false
  },
  {
    "de": "langatmig",
    "tr": "çox uzun, uzun uzadı",
    "fav": false
  },
  {
    "de": "laufend",
    "tr": "daima, davamlı",
    "fav": false
  },
  {
    "de": "lauschen",
    "tr": "dinləmək, qulaq vermək",
    "fav": false
  },
  {
    "de": "Laut",
    "tr": "səs, səda",
    "fav": false,
    "gender": "der"
  },
  {
    "de": "Lebensgefährte",
    "tr": "həyat yoldaşı",
    "fav": false,
    "gender": "der"
  },
  {
    "de": "lebhaft",
    "tr": "canlı, nəşəli",
    "fav": false
  },
  {
    "de": "lecker",
    "tr": "dadlı, ləziz",
    "fav": false
  },
  {
    "de": "lediglich",
    "tr": "yalnız, sadəcə, ancaq",
    "fav": false
  },
  {
    "de": "Leistung",
    "tr": "başarı, müvəffəqiyyət, performans",
    "fav": false,
    "gender": "die"
  },
  {
    "de": "Leitung haben",
    "tr": "kiməsə nəsə gec çatmaq (key)",
    "fav": false
  },
  {
    "de": "Leprakranke",
    "tr": "cüzzamlı xəstə",
    "fav": false,
    "gender": "der"
  },
  {
    "de": "lesenswert",
    "tr": "oxumağa dəyər, oxunmalı",
    "fav": false
  },
  {
    "de": "Lesestoff",
    "tr": "oxu materialı",
    "fav": false,
    "gender": "der"
  },
  {
    "de": "leuchten",
    "tr": "ışıldamaq, işıq saçmaq",
    "fav": false
  },
  {
    "de": "liefern",
    "tr": "təslim etmək, çatdırmaq",
    "fav": false
  },
  {
    "de": "Lieferung",
    "tr": "təslim, tədarük, çatdırılma",
    "fav": false,
    "gender": "die"
  },
  {
    "de": "loyal",
    "tr": "sadiq, bağlı",
    "fav": false
  },
  {
    "de": "lästig",
    "tr": "sıxıcı, bezgin",
    "fav": false
  },
  {
    "de": "lückenlos",
    "tr": "əksiksiz, tam, qüsursuz",
    "fav": false
  },
  {
    "de": "Macht",
    "tr": "güc, qüdrət, iqtidar",
    "fav": false,
    "gender": "die"
  },
  {
    "de": "magisch",
    "tr": "möcüzəli, sehrli",
    "fav": false
  },
  {
    "de": "Mangel",
    "tr": "əksiklik, çatışmazlıq",
    "fav": false,
    "gender": "der"
  },
  {
    "de": "Mannschaft",
    "tr": "komanda",
    "fav": false,
    "gender": "die"
  },
  {
    "de": "markant",
    "tr": "fərqli, diqqət çəkən, özəl",
    "fav": false
  },
  {
    "de": "Masse",
    "tr": "kütlə",
    "fav": false,
    "gender": "die"
  },
  {
    "de": "Mauer",
    "tr": "divar",
    "fav": false,
    "gender": "die"
  },
  {
    "de": "Maßnahme",
    "tr": "tədbir, önləm",
    "fav": false,
    "gender": "die"
  },
  {
    "de": "mehrmals",
    "tr": "bir neçə dəfə, təkrarən",
    "fav": false
  },
  {
    "de": "melden",
    "tr": "xəbər vermək, bildirmək",
    "fav": false
  },
  {
    "de": "menschenscheu",
    "tr": "çəkingən, utancaq",
    "fav": false
  },
  {
    "de": "merken",
    "tr": "fərqinə varmaq",
    "fav": false
  },
  {
    "de": "merken Dat (sich)",
    "tr": "əzbərləmək",
    "fav": false
  },
  {
    "de": "mindestens",
    "tr": "ən azı",
    "fav": false
  },
  {
    "de": "Mitglied",
    "tr": "üzv",
    "fav": false,
    "gender": "das"
  },
  {
    "de": "mithelfen + Gen",
    "tr": "köməyi ilə, yardımı ilə",
    "fav": false
  },
  {
    "de": "mitmachen",
    "tr": "qatılmaq, iştirak etmək",
    "fav": false
  },
  {
    "de": "mitteilen",
    "tr": "bildirmək, xəbər vermək",
    "fav": false
  },
  {
    "de": "mittlerweile",
    "tr": "eyni anda, bu arada",
    "fav": false
  },
  {
    "de": "Mut",
    "tr": "cəsarət",
    "fav": false,
    "gender": "der"
  },
  {
    "de": "mäßig",
    "tr": "orta dərəcəli, qıt",
    "fav": false
  },
  {
    "de": "Müdigkeit",
    "tr": "yorğunluq",
    "fav": false,
    "gender": "die"
  },
  {
    "de": "mühen (sich)",
    "tr": "arxasınca düşmək, əldə etməyə çalışmaq",
    "fav": false
  },
  {
    "de": "mühevoll",
    "tr": "zəhmətli, əziyyətli",
    "fav": false
  },
  {
    "de": "mühsam",
    "tr": "məşəqqətli, yorucu",
    "fav": false
  },
  {
    "de": "nach und nach",
    "tr": "yavaş-yavaş",
    "fav": false
  },
  {
    "de": "nach wie vor",
    "tr": "əvvəlki kimi",
    "fav": false
  },
  {
    "de": "Nachfrage",
    "tr": "tələb, istək",
    "fav": false,
    "gender": "die"
  },
  {
    "de": "Naschen",
    "tr": "dadma, dadına baxma",
    "fav": false,
    "gender": "das"
  },
  {
    "de": "nass",
    "tr": "yaş",
    "fav": false
  },
  {
    "de": "nebenan",
    "tr": "bitişik, yanaşı",
    "fav": false
  },
  {
    "de": "nehmen keine Notiz von + Dativ",
    "tr": "fikir verməmək, məhəl qoymamaq",
    "fav": false
  },
  {
    "de": "nennen",
    "tr": "demək, adlandırmaq",
    "fav": false
  },
  {
    "de": "Nervenkitzel",
    "tr": "həyəcan, qorxu, adrenalin",
    "fav": false,
    "gender": "der"
  },
  {
    "de": "Neugierde",
    "tr": "maraq",
    "fav": false,
    "gender": "die"
  },
  {
    "de": "nie zuvor",
    "tr": "daha öncə heç vaxt",
    "fav": false
  },
  {
    "de": "Niveau",
    "tr": "standart, səviyyə, dərəcə",
    "fav": false,
    "gender": "das"
  },
  {
    "de": "nix",
    "tr": "heç bir şey",
    "fav": false
  },
  {
    "de": "notwendig",
    "tr": "gərəkli, lazımlı, zəruri",
    "fav": false
  },
  {
    "de": "Ohnmacht",
    "tr": "bayılma, özündən getmə",
    "fav": false,
    "gender": "die"
  },
  {
    "de": "Pendeln",
    "tr": "gedib gəlmək",
    "fav": false
  },
  {
    "de": "Pflicht",
    "tr": "görəv, vəzifə, borc",
    "fav": false,
    "gender": "die"
  },
  {
    "de": "Plagen",
    "tr": "əzab vermək, yormaq, üzmək",
    "fav": false
  },
  {
    "de": "Platz verbrauchen",
    "tr": "yer tutmaq",
    "fav": false
  },
  {
    "de": "Pleite",
    "tr": "iflas, tənəzzül, bankrot",
    "fav": false,
    "gender": "die"
  },
  {
    "de": "plötzlich",
    "tr": "birdən-birə, anidən, qəfildən",
    "fav": false
  },
  {
    "de": "Quasi",
    "tr": "həmən, o dəqiqə",
    "fav": false
  },
  {
    "de": "Quasi über Nacht",
    "tr": "elə həmin gecə",
    "fav": false
  },
  {
    "de": "Quirlig",
    "tr": "həvəsli, coşqun, istəkli, həyat dolu",
    "fav": false
  },
  {
    "de": "Randgruppe",
    "tr": "azlıq",
    "fav": false,
    "gender": "die"
  },
  {
    "de": "Rasch",
    "tr": "tez, sürətlə",
    "fav": false
  },
  {
    "de": "Raten",
    "tr": "məsləhət görmək, məsləhət etmək",
    "fav": false
  },
  {
    "de": "ratifizieren",
    "tr": "dəstəkləmək",
    "fav": false
  },
  {
    "de": "rechtlich",
    "tr": "qanuni, hüquqi olaraq",
    "fav": false
  },
  {
    "de": "Regelmäßig",
    "tr": "müntəzəm, düzənli olaraq",
    "fav": false
  },
  {
    "de": "Regelrecht",
    "tr": "büsbütün, tamamən",
    "fav": false
  },
  {
    "de": "Reklamieren",
    "tr": "şikayət etmək",
    "fav": false
  },
  {
    "de": "Retten + vor Dat",
    "tr": "xilas etmək",
    "fav": false
  },
  {
    "de": "Rettung",
    "tr": "xilas, qurtuluş, yardım",
    "fav": false,
    "gender": "die"
  },
  {
    "de": "Riechen",
    "tr": "qoxlamaq, qoxmaq, iyləmək",
    "fav": false
  },
  {
    "de": "Riesig",
    "tr": "mükəmməl, şahanə, çox böyük",
    "fav": false
  },
  {
    "de": "Ruck-zuck",
    "tr": "cəld, tez",
    "fav": false
  },
  {
    "de": "Rufen nach Dat",
    "tr": "ardından çağırmaq, səslənmək",
    "fav": false
  },
  {
    "de": "Rutschen in Akk",
    "tr": "düşmək, sürüşüb düşmək",
    "fav": false
  },
  {
    "de": "Rückgang",
    "tr": "geriləmə, azalma",
    "fav": false,
    "gender": "der"
  },
  {
    "de": "sanft",
    "tr": "sakit, yumşaq, həlim",
    "fav": false
  },
  {
    "de": "Sarg",
    "tr": "tabut",
    "fav": false,
    "gender": "der"
  },
  {
    "de": "schaffen",
    "tr": "bacarmaq, çalışmaq, yaratmaq, daşımaq",
    "fav": false
  },
  {
    "de": "scheinen",
    "tr": "kimi görünmək, parıldamaq",
    "fav": false
  },
  {
    "de": "schenken",
    "tr": "doldurmaq, boşaltmaq",
    "fav": false
  },
  {
    "de": "Schicksal",
    "tr": "qismət, tale, bəxt",
    "fav": false,
    "gender": "das"
  },
  {
    "de": "schief",
    "tr": "əyri, yalnış, tərs",
    "fav": false
  },
  {
    "de": "schier",
    "tr": "sanki, yalnız, dərhal, saf",
    "fav": false
  },
  {
    "de": "schimpfen",
    "tr": "söymək, danlamaq",
    "fav": false
  },
  {
    "de": "schließen",
    "tr": "bitirmək, tamamlamaq, kilidləmək",
    "fav": false
  },
  {
    "de": "schließlich",
    "tr": "sonunda, nəhayət",
    "fav": false
  },
  {
    "de": "Schmerzen zufügen (einem Tier)",
    "tr": "əzab, ağrı vermək",
    "fav": false
  },
  {
    "de": "schuften",
    "tr": "eşşək kimi çalışmaq",
    "fav": false
  },
  {
    "de": "Schulden",
    "tr": "borclar",
    "fav": false,
    "gender": "die"
  },
  {
    "de": "schulen",
    "tr": "öyrətmək, alışdırmaq",
    "fav": false
  },
  {
    "de": "schwärmen",
    "tr": "həyəcanla anlatmaq",
    "fav": false
  },
  {
    "de": "schüchtern",
    "tr": "çəkingən, utancaq",
    "fav": false
  },
  {
    "de": "Sehnsucht",
    "tr": "həsrət",
    "fav": false,
    "gender": "die"
  },
  {
    "de": "sein in + Dativ + tatig",
    "tr": "kimi çalışmaq",
    "fav": false
  },
  {
    "de": "selbstbewußt",
    "tr": "özünə güvənən",
    "fav": false
  },
  {
    "de": "selbstständig",
    "tr": "sərbəst, müstəqil",
    "fav": false
  },
  {
    "de": "setzen sich für + Akk ein",
    "tr": "dəstəkləmək, tərəfini tutmaq",
    "fav": false
  },
  {
    "de": "sichern",
    "tr": "sağlamaq, təmin etmək",
    "fav": false
  },
  {
    "de": "sinnlos",
    "tr": "əbəs yerə, boşuna",
    "fav": false
  },
  {
    "de": "skeptisch",
    "tr": "şübhəli, bəlirsiz, qaranlıq",
    "fav": false
  },
  {
    "de": "sofort",
    "tr": "dərhal, həmən",
    "fav": false
  },
  {
    "de": "sowie",
    "tr": "eləcə də, həm də",
    "fav": false
  },
  {
    "de": "speisen",
    "tr": "yemək, yedirtmək",
    "fav": false
  },
  {
    "de": "spenden an Akk",
    "tr": "dağıtmaq, bağışlamaq",
    "fav": false
  },
  {
    "de": "spucken",
    "tr": "tüpürmək, qusmaq",
    "fav": false
  },
  {
    "de": "spüren",
    "tr": "duymaq, hiss etmək",
    "fav": false
  },
  {
    "de": "stammen",
    "tr": "çıxmaq, gəlmək, soyundan gəlmək",
    "fav": false
  },
  {
    "de": "Standbein",
    "tr": "dolanışıq yeri, ən böyük dəstək, gəlir yeri",
    "fav": false,
    "gender": "das"
  },
  {
    "de": "stattfinden",
    "tr": "baş tutmaq, olub bitmək",
    "fav": false
  },
  {
    "de": "stecken",
    "tr": "içində olmaq",
    "fav": false
  },
  {
    "de": "stehen für Akk",
    "tr": "təmsil etmək, izah etmək",
    "fav": false
  },
  {
    "de": "steigen",
    "tr": "qalxmaq, artmaq, çoxalmaq",
    "fav": false
  },
  {
    "de": "stellenweise",
    "tr": "yeri gəldikcə, ara-sıra",
    "fav": false
  },
  {
    "de": "steuern",
    "tr": "idarə etmə, yönəltmə",
    "fav": false,
    "gender": "das"
  },
  {
    "de": "stoßen",
    "tr": "itələmək, təpik atmaq, yumruq vurmaq",
    "fav": false
  },
  {
    "de": "Streifen",
    "tr": "dolaşmaq, gəzmək, toxunmaq",
    "fav": false
  },
  {
    "de": "Streifenhörnchen",
    "tr": "sincab",
    "fav": false,
    "gender": "das"
  },
  {
    "de": "Strömung",
    "tr": "axın",
    "fav": false,
    "gender": "die"
  },
  {
    "de": "ständig",
    "tr": "daima, fasiləsiz",
    "fav": false
  },
  {
    "de": "Stöbern",
    "tr": "araşdırmaq, gözdən keçirmək, eşələmək",
    "fav": false
  },
  {
    "de": "stören + Akk",
    "tr": "mane olmaq, narahat etmək",
    "fav": false
  },
  {
    "de": "Sucht",
    "tr": "düşkünlük, tutqu",
    "fav": false
  },
  {
    "de": "süchtig",
    "tr": "düşkün, bağlı, tutqun",
    "fav": false
  },
  {
    "de": "Talent",
    "tr": "istedad",
    "fav": false,
    "gender": "das"
  },
  {
    "de": "talentiert",
    "tr": "istedadlı, yetənəkli",
    "fav": false
  },
  {
    "de": "tatsächlich",
    "tr": "həqiqi, gerçək, həqiqətən",
    "fav": false
  },
  {
    "de": "tauchen",
    "tr": "dalmaq, batmaq",
    "fav": false
  },
  {
    "de": "teilnehmen",
    "tr": "iştirak etmək",
    "fav": false
  },
  {
    "de": "teilweise",
    "tr": "qismən",
    "fav": false
  },
  {
    "de": "tragen",
    "tr": "daşımaq",
    "fav": false
  },
  {
    "de": "trennen, sich",
    "tr": "ayrılmaq",
    "fav": false
  },
  {
    "de": "Träne",
    "tr": "gözyaşı",
    "fav": false,
    "gender": "die"
  },
  {
    "de": "tätig sein",
    "tr": "bir yerdə çalışmaq, işləmək",
    "fav": false
  },
  {
    "de": "Tätigkeit",
    "tr": "iş, məslək, fəaliyyət",
    "fav": false,
    "gender": "die"
  },
  {
    "de": "Ufer",
    "tr": "sahil, kənar",
    "fav": false,
    "gender": "das"
  },
  {
    "de": "umbauen",
    "tr": "dəyişiklik etmək, dəyişmək",
    "fav": false
  },
  {
    "de": "umfassend",
    "tr": "geniş, artıq",
    "fav": false
  },
  {
    "de": "umgehen",
    "tr": "davranmaq, baş etmək",
    "fav": false
  },
  {
    "de": "umgekehrt",
    "tr": "tərs, əks, əksinə",
    "fav": false
  },
  {
    "de": "umkreisen",
    "tr": "dövrə vurmaq, ətrafında dönmək",
    "fav": false
  },
  {
    "de": "umsetzen",
    "tr": "gerçəkləşdirmək, həyata keçirmək",
    "fav": false
  },
  {
    "de": "unappetitlich",
    "tr": "dadsız, iştahqaçırdan",
    "fav": false
  },
  {
    "de": "unerreichbar",
    "tr": "əlçatmaz",
    "fav": false
  },
  {
    "de": "unerwünscht",
    "tr": "istəməyən",
    "fav": false
  },
  {
    "de": "Unfall",
    "tr": "qəza",
    "fav": false,
    "gender": "der"
  },
  {
    "de": "Ungeduld",
    "tr": "səbirsizlik",
    "fav": false,
    "gender": "das"
  },
  {
    "de": "ungewöhnlich",
    "tr": "qeyri adi, fərqli, alışılmamış",
    "fav": false
  },
  {
    "de": "unglaublich",
    "tr": "inanılmaz",
    "fav": false
  },
  {
    "de": "untergehen",
    "tr": "batmaq, çökmək",
    "fav": false
  },
  {
    "de": "Unterlagen",
    "tr": "sənədlər",
    "fav": false,
    "gender": "die"
  },
  {
    "de": "unterstützen",
    "tr": "dəstəkləmək",
    "fav": false
  },
  {
    "de": "Ursache",
    "tr": "nədən, səbəb",
    "fav": false,
    "gender": "die"
  },
  {
    "de": "variabel",
    "tr": "qərarsız, dəyişkən, dəyişik",
    "fav": false
  },
  {
    "de": "verabreden sich",
    "tr": "sözləşmək",
    "fav": false
  },
  {
    "de": "verantwortlich sein + für Akk",
    "tr": "məsul, məsuliyyətli, sorumlu",
    "fav": false
  },
  {
    "de": "verbrauchen",
    "tr": "sərf etmək, tükətmək",
    "fav": false
  },
  {
    "de": "verdrängen",
    "tr": "atmaq, yerindən etmək",
    "fav": false
  },
  {
    "de": "verfolgen",
    "tr": "izləmək, təqib etmək",
    "fav": false
  },
  {
    "de": "verfügen über Akk",
    "tr": "sahib olmaq",
    "fav": false
  },
  {
    "de": "vergnügen",
    "tr": "zövq, həzz, məmnuniyyət",
    "fav": false,
    "gender": "das"
  },
  {
    "de": "verlagern",
    "tr": "nəql etmək, yerini dəyişdirmək",
    "fav": false
  },
  {
    "de": "verlangen",
    "tr": "tələb etmək, istəmək",
    "fav": false
  },
  {
    "de": "verlernen",
    "tr": "öyrəndiyin unutmaq, tərgitmə",
    "fav": false
  },
  {
    "de": "verletzen (+an Dativ)",
    "tr": "yararlanmaq",
    "fav": false
  },
  {
    "de": "verlieren sich",
    "tr": "itmək, yoxa çıxmaq",
    "fav": false
  },
  {
    "de": "verloben sich",
    "tr": "nişanlanmaq",
    "fav": false
  },
  {
    "de": "verlängern",
    "tr": "uzatmaq",
    "fav": false
  },
  {
    "de": "vermeintlich",
    "tr": "yalandan, sözdə, saxta",
    "fav": false
  },
  {
    "de": "vermindern",
    "tr": "azaltmaq, aşağı salmaq",
    "fav": false
  },
  {
    "de": "vermissen",
    "tr": "darıxmaq, yoxluğun hiss etmək",
    "fav": false
  },
  {
    "de": "Vermunt",
    "tr": "məntiq",
    "fav": false,
    "gender": "die"
  },
  {
    "de": "vermuten",
    "tr": "sanmaq, fərz etmək, təxmin etmək",
    "fav": false
  },
  {
    "de": "Vermögen",
    "tr": "sərvət, varlıq, mal",
    "fav": false,
    "gender": "das"
  },
  {
    "de": "verpassen",
    "tr": "qaçırmaq, buraxma",
    "fav": false
  },
  {
    "de": "verraten",
    "tr": "ifşa etmək, açığa çıxartmaq, satmaq",
    "fav": false
  },
  {
    "de": "verschlingen",
    "tr": "silib süpürmək, udmaq",
    "fav": false
  },
  {
    "de": "verschwiegen",
    "tr": "ağzı sıx, ağzı bütöv, söz danışmayan",
    "fav": false
  },
  {
    "de": "verschwinden",
    "tr": "yox olmaq, yoxa çıxmaq",
    "fav": false
  },
  {
    "de": "versehentlich",
    "tr": "yanlışlıqla, diqqətsizlik üzündən",
    "fav": false
  },
  {
    "de": "versprechen",
    "tr": "ümidli olmaq, söz vermək, bildirmək",
    "fav": false
  },
  {
    "de": "verstecken sich",
    "tr": "saxlanmaq, gizlənmək",
    "fav": false
  },
  {
    "de": "verstellen",
    "tr": "yerin dəyişdirmək",
    "fav": false
  },
  {
    "de": "verständigen",
    "tr": "anlatmaq, bir-birinə açılmaq",
    "fav": false
  },
  {
    "de": "verständnisvoll",
    "tr": "anlayışlı",
    "fav": false
  },
  {
    "de": "versuchen",
    "tr": "çalışmaq, səy göstərmək",
    "fav": false
  },
  {
    "de": "vertrauen",
    "tr": "inanmaq, güvənmək",
    "fav": false
  },
  {
    "de": "verträumt",
    "tr": "dalğın, səssiz, xəyalpərəst",
    "fav": false
  },
  {
    "de": "verurteilen",
    "tr": "qınamaq, hökm vermək",
    "fav": false
  },
  {
    "de": "verwenden",
    "tr": "istifadə etmək, sərf etmək",
    "fav": false
  },
  {
    "de": "verwirklichen",
    "tr": "gerçəkləşdirmək",
    "fav": false
  },
  {
    "de": "verwitwet",
    "tr": "dul",
    "fav": false
  },
  {
    "de": "verzeihen",
    "tr": "əfv etmək, bağışlamaq",
    "fav": false
  },
  {
    "de": "Verzeihung",
    "tr": "Bağışlayın!",
    "fav": false
  },
  {
    "de": "verzweifeln",
    "tr": "ümidsizliyə düşmək",
    "fav": false
  },
  {
    "de": "verzweifelt",
    "tr": "çarəsiz, ümidsiz",
    "fav": false
  },
  {
    "de": "verärgert",
    "tr": "qəzəbli, canı sıxılmış, üzülmüş, üzgün",
    "fav": false
  },
  {
    "de": "vielfaches",
    "tr": "çeşidli, hər cürə",
    "fav": false
  },
  {
    "de": "voraussetzen",
    "tr": "şərt qoymaq",
    "fav": false
  },
  {
    "de": "vorher",
    "tr": "bundan əvvəl, öncədən",
    "fav": false
  },
  {
    "de": "Vorschlag",
    "tr": "təklif",
    "fav": false,
    "gender": "der"
  },
  {
    "de": "Vorsorge",
    "tr": "tədbir, önləm",
    "fav": false,
    "gender": "die"
  },
  {
    "de": "Vorurteil",
    "tr": "qınaq, önyarğı",
    "fav": false,
    "gender": "der"
  },
  {
    "de": "vorweg",
    "tr": "öncədən",
    "fav": false
  },
  {
    "de": "wberzeugen Akk von Dat",
    "tr": "inandırmaq, yola gətirmək",
    "fav": false
  },
  {
    "de": "Wechsel",
    "tr": "dəyişiklik, dəyişim",
    "fav": false,
    "gender": "der"
  },
  {
    "de": "wegen + Gen",
    "tr": "görə",
    "fav": false
  },
  {
    "de": "weglegen",
    "tr": "bir yana qoymaq",
    "fav": false
  },
  {
    "de": "wegwerfen",
    "tr": "başından atmaq, tullamaq",
    "fav": false
  },
  {
    "de": "weitergehen",
    "tr": "davam etmək, yoluna davam etmək",
    "fav": false
  },
  {
    "de": "weiterhin",
    "tr": "bundan başqa, ayrıca",
    "fav": false
  },
  {
    "de": "weitsichtig",
    "tr": "uzaqgörən",
    "fav": false
  },
  {
    "de": "weltfremd",
    "tr": "qəribə, fantastik, əcayib",
    "fav": false
  },
  {
    "de": "weltweit",
    "tr": "bütün dünyada",
    "fav": false
  },
  {
    "de": "werben",
    "tr": "reklam etmək, təbliğ etmək",
    "fav": false
  },
  {
    "de": "wickeln",
    "tr": "sarmaq, dolamaq (ətrafını)",
    "fav": false
  },
  {
    "de": "widmen sich",
    "tr": "özünü həsr etmək, əlləşmək",
    "fav": false
  },
  {
    "de": "wiegen",
    "tr": "ağırlığında olmaq",
    "fav": false
  },
  {
    "de": "wild",
    "tr": "vəhşi",
    "fav": false
  },
  {
    "de": "Winken",
    "tr": "əl sallama",
    "fav": false,
    "gender": "das"
  },
  {
    "de": "wirken",
    "tr": "təsir etmək",
    "fav": false
  },
  {
    "de": "witzig",
    "tr": "komik, zarafatcıl",
    "fav": false
  },
  {
    "de": "woanders",
    "tr": "başqa yerdə",
    "fav": false
  },
  {
    "de": "wohl",
    "tr": "isə də, əcaba, mübahisəsiz, deyəsən",
    "fav": false
  },
  {
    "de": "wohlfühlen, sich",
    "tr": "özünü yaxşı hiss etmək",
    "fav": false
  },
  {
    "de": "Wohnheim",
    "tr": "yataqxana, pansionat",
    "fav": false,
    "gender": "das"
  },
  {
    "de": "womöglich",
    "tr": "mümkünsə, bəlkə də",
    "fav": false
  },
  {
    "de": "Wortergreifen",
    "tr": "söz almaq",
    "fav": false,
    "gender": "das"
  },
  {
    "de": "wünschenswert",
    "tr": "arzu edilən, istənən",
    "fav": false
  },
  {
    "de": "Zeitvertreiben, sich",
    "tr": "vaxtın keçirtmək",
    "fav": false
  },
  {
    "de": "zerstören",
    "tr": "yıxmaq, yox etmək",
    "fav": false
  },
  {
    "de": "zierlich",
    "tr": "zərif, incə, mükəmməl bir şey",
    "fav": false
  },
  {
    "de": "zu viert",
    "tr": "dördlükdə",
    "fav": false
  },
  {
    "de": "zudem",
    "tr": "bundan başqa, üstəlik",
    "fav": false
  },
  {
    "de": "Zufall überlassen (dem)",
    "tr": "təsadüfə buraxmaq",
    "fav": false
  },
  {
    "de": "zufrieden sein + mit Dat",
    "tr": "razı qalmaq",
    "fav": false
  },
  {
    "de": "zufällig",
    "tr": "təsadüfən",
    "fav": false
  },
  {
    "de": "zugleich",
    "tr": "eyni anda, bu arada, eyni əsnada",
    "fav": false
  },
  {
    "de": "zulassen",
    "tr": "icazə vermək, içəri buraxmaq",
    "fav": false
  },
  {
    "de": "zuletzt",
    "tr": "son olaraq, nəhayət, sonunda",
    "fav": false
  },
  {
    "de": "zumal",
    "tr": "ən başda, özəlliklə",
    "fav": false
  },
  {
    "de": "zunehmen",
    "tr": "artmaq, kökəlmək",
    "fav": false
  },
  {
    "de": "zurückfordern",
    "tr": "geri istəmək",
    "fav": false
  },
  {
    "de": "zurückhaben",
    "tr": "geri almaq",
    "fav": false
  },
  {
    "de": "zurückkehren",
    "tr": "geri dönmək",
    "fav": false
  },
  {
    "de": "zusammenfassen",
    "tr": "xülasə vermək, toplamaq",
    "fav": false
  },
  {
    "de": "zusprechen",
    "tr": "vəsiyət etmək, səlahiyyətinə vermək",
    "fav": false
  },
  {
    "de": "Zuspruch finden",
    "tr": "rəğbət qazanmaq",
    "fav": false
  },
  {
    "de": "zuverlässig",
    "tr": "etibarlı",
    "fav": false
  },
  {
    "de": "zwar",
    "tr": "olsa da",
    "fav": false
  },
  {
    "de": "zweckmäßig",
    "tr": "yararlı, istifadə olunan, məqsədə uyğun",
    "fav": false
  },
  {
    "de": "zweierlei",
    "tr": "iki cür",
    "fav": false
  },
  {
    "de": "zwerk",
    "tr": "məqsəd, niyyət, hədəf",
    "fav": false,
    "gender": "der"
  },
  {
    "de": "zwingen",
    "tr": "məcbur etmək, zorlamaq",
    "fav": false
  },
  {
    "de": "ändern",
    "tr": "dəyişdirmək, təhrif etmək",
    "fav": false
  },
  {
    "de": "ängstlich",
    "tr": "qorxaq, təlaşlı",
    "fav": false
  },
  {
    "de": "Ärmste",
    "tr": "kasıb, zavallı, yazıq",
    "fav": false,
    "gender": "der"
  },
  {
    "de": "überfordert sein",
    "tr": "tükənmiş olmaq, əzilmiş, boğulmuş olmaq",
    "fav": false
  },
  {
    "de": "überhören",
    "tr": "eşitməmək, eşitməzlikdən gəlmək",
    "fav": false
  },
  {
    "de": "überleben",
    "tr": "qurtulmaq, həyatda qalmaq",
    "fav": false
  },
  {
    "de": "überlegen",
    "tr": "düşünüb daşınmaq",
    "fav": false
  },
  {
    "de": "überqueren",
    "tr": "keçmək, qarşı tərəfə keçmək",
    "fav": false
  },
  {
    "de": "überraschen",
    "tr": "heyrətləndirmək",
    "fav": false
  },
  {
    "de": "überstehen",
    "tr": "atlatmak, aşmaq",
    "fav": false
  },
  {
    "de": "übertreiben",
    "tr": "böyütmək, şişirtmək",
    "fav": false
  },
  {
    "de": "üblich sein",
    "tr": "adət olmaq, sıradan bir şey, alışılmış",
    "fav": false
  }
]
